{
  "rows": [
    {
      "run": "v4_full_n06_a04_ct045_b1d1_2026_04_10",
      "path": ".analysis\\v4_full_n06_a04_ct045_b1d1_2026_04_10.json",
      "iter": 40,
      "max_depth": 1,
      "v3_depth": 1,
      "branch": 1,
      "max_validations": 25,
      "max_patch": 40,
      "max_per_node": 10,
      "time_budget": 20.0,
      "ct": 0.45,
      "nw": 0.6,
      "aw": 0.4,
      "h_rep": 3,
      "h_att": 20,
      "h_rate": 0.15,
      "h_avg_val": 19.7,
      "h_avg_time": 48.993337760015855,
      "l_rep": 3,
      "l_att": 20,
      "l_rate": 0.15,
      "l_avg_val": 24.95,
      "l_avg_time": 58.180249605036806,
      "h_top_bucket": "VALIDATION_BUDGET_EXHAUSTED",
      "l_top_bucket": "VALIDATION_BUDGET_EXHAUSTED"
    },
    {
      "run": "v4_full_n06_a04_ct000_b1d1_2026_04_10",
      "path": ".analysis\\v4_full_n06_a04_ct000_b1d1_2026_04_10.json",
      "iter": 40,
      "max_depth": 1,
      "v3_depth": 1,
      "branch": 1,
      "max_validations": 25,
      "max_patch": 40,
      "max_per_node": 10,
      "time_budget": 20.0,
      "ct": 0.0,
      "nw": 0.6,
      "aw": 0.4,
      "h_rep": 3,
      "h_att": 20,
      "h_rate": 0.15,
      "h_avg_val": 24.95,
      "h_avg_time": 45.60800076501327,
      "l_rep": 3,
      "l_att": 20,
      "l_rate": 0.15,
      "l_avg_val": 24.95,
      "l_avg_time": 44.69683119499823,
      "h_top_bucket": "VALIDATION_BUDGET_EXHAUSTED",
      "l_top_bucket": "VALIDATION_BUDGET_EXHAUSTED"
    },
    {
      "run": "v4_full_n02_a08_ct045_b1d1_2026_04_10",
      "path": ".analysis\\v4_full_n02_a08_ct045_b1d1_2026_04_10.json",
      "iter": 40,
      "max_depth": 1,
      "v3_depth": 1,
      "branch": 1,
      "max_validations": 25,
      "max_patch": 40,
      "max_per_node": 10,
      "time_budget": 20.0,
      "ct": 0.45,
      "nw": 0.2,
      "aw": 0.8,
      "h_rep": 3,
      "h_att": 20,
      "h_rate": 0.15,
      "h_avg_val": 19.15,
      "h_avg_time": 36.51312859499594,
      "l_rep": 3,
      "l_att": 20,
      "l_rate": 0.15,
      "l_avg_val": 24.55,
      "l_avg_time": 44.49955362500041,
      "h_top_bucket": "VALIDATION_BUDGET_EXHAUSTED",
      "l_top_bucket": "VALIDATION_BUDGET_EXHAUSTED"
    },
    {
      "run": "v4_full_n02_a08_ct000_b1d1_2026_04_10",
      "path": ".analysis\\v4_full_n02_a08_ct000_b1d1_2026_04_10.json",
      "iter": 40,
      "max_depth": 1,
      "v3_depth": 1,
      "branch": 1,
      "max_validations": 25,
      "max_patch": 40,
      "max_per_node": 10,
      "time_budget": 20.0,
      "ct": 0.0,
      "nw": 0.2,
      "aw": 0.8,
      "h_rep": 3,
      "h_att": 20,
      "h_rate": 0.15,
      "h_avg_val": 24.55,
      "h_avg_time": 887.2223288000096,
      "l_rep": 3,
      "l_att": 20,
      "l_rate": 0.15,
      "l_avg_val": 24.55,
      "l_avg_time": 57.074285819986834,
      "h_top_bucket": "VALIDATION_BUDGET_EXHAUSTED",
      "l_top_bucket": "VALIDATION_BUDGET_EXHAUSTED"
    },
    {
      "run": "v4_v3only_unchoked_policy500_ct000_b1d1_2026_04_10",
      "path": ".analysis\\v4_v3only_unchoked_policy500_ct000_b1d1_2026_04_10.json",
      "iter": 40,
      "max_depth": 1,
      "v3_depth": 1,
      "branch": 1,
      "max_validations": 25,
      "max_patch": 500,
      "max_per_node": 10,
      "time_budget": 20.0,
      "ct": 0.0,
      "nw": 0.6,
      "aw": 0.4,
      "h_rep": 3,
      "h_att": 20,
      "h_rate": 0.15,
      "h_avg_val": 25.0,
      "h_avg_time": 76.62978000001166,
      "l_rep": 3,
      "l_att": 20,
      "l_rate": 0.15,
      "l_avg_val": 25.0,
      "l_avg_time": 76.91647630999213,
      "h_top_bucket": "VALIDATION_BUDGET_EXHAUSTED",
      "l_top_bucket": "VALIDATION_BUDGET_EXHAUSTED"
    },
    {
      "run": "v4_v3only_unchoked_critic500_ct060_b1d1_2026_04_10",
      "path": ".analysis\\v4_v3only_unchoked_critic500_ct060_b1d1_2026_04_10.json",
      "iter": 40,
      "max_depth": 1,
      "v3_depth": 1,
      "branch": 1,
      "max_validations": 25,
      "max_patch": 500,
      "max_per_node": 10,
      "time_budget": 20.0,
      "ct": 0.6,
      "nw": 0.6,
      "aw": 0.4,
      "h_rep": 2,
      "h_att": 20,
      "h_rate": 0.1,
      "h_avg_val": 6.5,
      "h_avg_time": 24.86247556996532,
      "l_rep": 3,
      "l_att": 20,
      "l_rate": 0.15,
      "l_avg_val": 25.0,
      "l_avg_time": 67.15974833999644,
      "h_top_bucket": "CRITIC_GATE_OVERFILTERING",
      "l_top_bucket": "VALIDATION_BUDGET_EXHAUSTED"
    },
    {
      "run": "v4_v3sniper_V1_control_val025_2026_04_11_030623",
      "path": ".analysis\\sniper_suite_2026_04_11_030623\\runs\\v4_v3sniper_V1_control_val025_2026_04_11_030623.json",
      "iter": 40,
      "max_depth": 1,
      "v3_depth": 1,
      "branch": 1,
      "max_validations": 25,
      "max_patch": 500,
      "max_per_node": 10,
      "time_budget": 20.0,
      "ct": 0.0,
      "nw": 0.6,
      "aw": 0.4,
      "h_rep": 3,
      "h_att": 20,
      "h_rate": 0.15,
      "h_avg_val": 25.0,
      "h_avg_time": 34.34767531502293,
      "l_rep": 3,
      "l_att": 20,
      "l_rate": 0.15,
      "l_avg_val": 25.0,
      "l_avg_time": 30.420854504976887,
      "h_top_bucket": "VALIDATION_BUDGET_EXHAUSTED",
      "l_top_bucket": "VALIDATION_BUDGET_EXHAUSTED"
    },
    {
      "run": "v4_v3sniper_V2_val050_2026_04_11_030623",
      "path": ".analysis\\sniper_suite_2026_04_11_030623\\runs\\v4_v3sniper_V2_val050_2026_04_11_030623.json",
      "iter": 40,
      "max_depth": 1,
      "v3_depth": 1,
      "branch": 1,
      "max_validations": 50,
      "max_patch": 500,
      "max_per_node": 10,
      "time_budget": 20.0,
      "ct": 0.0,
      "nw": 0.6,
      "aw": 0.4,
      "h_rep": 5,
      "h_att": 20,
      "h_rate": 0.25,
      "h_avg_val": 49.4,
      "h_avg_time": 66.37302800004836,
      "l_rep": 5,
      "l_att": 20,
      "l_rate": 0.25,
      "l_avg_val": 49.4,
      "l_avg_time": 58.23237676500575,
      "h_top_bucket": "VALIDATION_BUDGET_EXHAUSTED",
      "l_top_bucket": "VALIDATION_BUDGET_EXHAUSTED"
    },
    {
      "run": "v4_v3sniper_V3_val100_2026_04_11_030623",
      "path": ".analysis\\sniper_suite_2026_04_11_030623\\runs\\v4_v3sniper_V3_val100_2026_04_11_030623.json",
      "iter": 40,
      "max_depth": 1,
      "v3_depth": 1,
      "branch": 1,
      "max_validations": 100,
      "max_patch": 500,
      "max_per_node": 10,
      "time_budget": 20.0,
      "ct": 0.0,
      "nw": 0.6,
      "aw": 0.4,
      "h_rep": 6,
      "h_att": 20,
      "h_rate": 0.3,
      "h_avg_val": 91.4,
      "h_avg_time": 924.5150653150049,
      "l_rep": 6,
      "l_att": 20,
      "l_rate": 0.3,
      "l_avg_val": 91.4,
      "l_avg_time": 106.48388353999471,
      "h_top_bucket": "VALIDATION_BUDGET_EXHAUSTED",
      "l_top_bucket": "VALIDATION_BUDGET_EXHAUSTED"
    },
    {
      "run": "v4_v3sniper_V4_val150_2026_04_11_030623",
      "path": ".analysis\\sniper_suite_2026_04_11_030623\\runs\\v4_v3sniper_V4_val150_2026_04_11_030623.json",
      "iter": 40,
      "max_depth": 1,
      "v3_depth": 1,
      "branch": 1,
      "max_validations": 150,
      "max_patch": 500,
      "max_per_node": 10,
      "time_budget": 25.0,
      "ct": 0.0,
      "nw": 0.6,
      "aw": 0.4,
      "h_rep": 8,
      "h_att": 20,
      "h_rate": 0.4,
      "h_avg_val": 118.55,
      "h_avg_time": 193.89087613999146,
      "l_rep": 8,
      "l_att": 20,
      "l_rate": 0.4,
      "l_avg_val": 118.55,
      "l_avg_time": 270.65993123998635,
      "h_top_bucket": "VALIDATED_NOT_PLAUSIBLE",
      "l_top_bucket": "VALIDATED_NOT_PLAUSIBLE"
    },
    {
      "run": "v4_v3sniper_V5_val200_2026_04_11_030623",
      "path": ".analysis\\sniper_suite_2026_04_11_030623\\runs\\v4_v3sniper_V5_val200_2026_04_11_030623.json",
      "iter": 40,
      "max_depth": 1,
      "v3_depth": 1,
      "branch": 1,
      "max_validations": 200,
      "max_patch": 500,
      "max_per_node": 10,
      "time_budget": 30.0,
      "ct": 0.0,
      "nw": 0.6,
      "aw": 0.4,
      "h_rep": 9,
      "h_att": 20,
      "h_rate": 0.45,
      "h_avg_val": 136.0,
      "h_avg_time": 398.3809241349809,
      "l_rep": 9,
      "l_att": 20,
      "l_rate": 0.45,
      "l_avg_val": 136.0,
      "l_avg_time": 363.4847989650094,
      "h_top_bucket": "VALIDATED_NOT_PLAUSIBLE",
      "l_top_bucket": "VALIDATED_NOT_PLAUSIBLE"
    }
  ],
  "ablations": {
    "critic_full_n06": {
      "h_rep_delta": 0,
      "l_rep_delta": 0,
      "h_rate_delta": 0.0,
      "l_rate_delta": 0.0,
      "h_avg_val_delta": -5.25,
      "l_avg_val_delta": 0.0
    },
    "critic_full_n02": {
      "h_rep_delta": 0,
      "l_rep_delta": 0,
      "h_rate_delta": 0.0,
      "l_rate_delta": 0.0,
      "h_avg_val_delta": -5.4,
      "l_avg_val_delta": 0.0
    },
    "critic_unchoked": {
      "h_rep_delta": -1,
      "l_rep_delta": 0,
      "h_rate_delta": -0.05,
      "l_rate_delta": 0.0,
      "h_avg_val_delta": -18.5,
      "l_avg_val_delta": 0.0
    },
    "weight_ct000": {
      "h_rep_delta": 0,
      "l_rep_delta": 0,
      "h_rate_delta": 0.0,
      "l_rate_delta": 0.0,
      "h_avg_val_delta": -0.4,
      "l_avg_val_delta": -0.4
    },
    "weight_ct045": {
      "h_rep_delta": 0,
      "l_rep_delta": 0,
      "h_rate_delta": 0.0,
      "l_rate_delta": 0.0,
      "h_avg_val_delta": -0.55,
      "l_avg_val_delta": -0.4
    },
    "overnight_vs_v1": {
      "v4_v3sniper_V1_control_val025_2026_04_11_030623": {
        "val": 25,
        "h_rep": 3,
        "l_rep": 3,
        "h_delta": 0,
        "l_delta": 0,
        "h_top_bucket": "VALIDATION_BUDGET_EXHAUSTED",
        "l_top_bucket": "VALIDATION_BUDGET_EXHAUSTED"
      },
      "v4_v3sniper_V2_val050_2026_04_11_030623": {
        "val": 50,
        "h_rep": 5,
        "l_rep": 5,
        "h_delta": 2,
        "l_delta": 2,
        "h_top_bucket": "VALIDATION_BUDGET_EXHAUSTED",
        "l_top_bucket": "VALIDATION_BUDGET_EXHAUSTED"
      },
      "v4_v3sniper_V3_val100_2026_04_11_030623": {
        "val": 100,
        "h_rep": 6,
        "l_rep": 6,
        "h_delta": 3,
        "l_delta": 3,
        "h_top_bucket": "VALIDATION_BUDGET_EXHAUSTED",
        "l_top_bucket": "VALIDATION_BUDGET_EXHAUSTED"
      },
      "v4_v3sniper_V4_val150_2026_04_11_030623": {
        "val": 150,
        "h_rep": 8,
        "l_rep": 8,
        "h_delta": 5,
        "l_delta": 5,
        "h_top_bucket": "VALIDATED_NOT_PLAUSIBLE",
        "l_top_bucket": "VALIDATED_NOT_PLAUSIBLE"
      },
      "v4_v3sniper_V5_val200_2026_04_11_030623": {
        "val": 200,
        "h_rep": 9,
        "l_rep": 9,
        "h_delta": 6,
        "l_delta": 6,
        "h_top_bucket": "VALIDATED_NOT_PLAUSIBLE",
        "l_top_bucket": "VALIDATED_NOT_PLAUSIBLE"
      }
    }
  },
  "best": {
    "hybrid": {
      "run": "v4_v3sniper_V5_val200_2026_04_11_030623",
      "path": ".analysis\\sniper_suite_2026_04_11_030623\\runs\\v4_v3sniper_V5_val200_2026_04_11_030623.json",
      "iter": 40,
      "max_depth": 1,
      "v3_depth": 1,
      "branch": 1,
      "max_validations": 200,
      "max_patch": 500,
      "max_per_node": 10,
      "time_budget": 30.0,
      "ct": 0.0,
      "nw": 0.6,
      "aw": 0.4,
      "h_rep": 9,
      "h_att": 20,
      "h_rate": 0.45,
      "h_avg_val": 136.0,
      "h_avg_time": 398.3809241349809,
      "l_rep": 9,
      "l_att": 20,
      "l_rate": 0.45,
      "l_avg_val": 136.0,
      "l_avg_time": 363.4847989650094,
      "h_top_bucket": "VALIDATED_NOT_PLAUSIBLE",
      "l_top_bucket": "VALIDATED_NOT_PLAUSIBLE"
    },
    "latent": {
      "run": "v4_v3sniper_V5_val200_2026_04_11_030623",
      "path": ".analysis\\sniper_suite_2026_04_11_030623\\runs\\v4_v3sniper_V5_val200_2026_04_11_030623.json",
      "iter": 40,
      "max_depth": 1,
      "v3_depth": 1,
      "branch": 1,
      "max_validations": 200,
      "max_patch": 500,
      "max_per_node": 10,
      "time_budget": 30.0,
      "ct": 0.0,
      "nw": 0.6,
      "aw": 0.4,
      "h_rep": 9,
      "h_att": 20,
      "h_rate": 0.45,
      "h_avg_val": 136.0,
      "h_avg_time": 398.3809241349809,
      "l_rep": 9,
      "l_att": 20,
      "l_rate": 0.45,
      "l_avg_val": 136.0,
      "l_avg_time": 363.4847989650094,
      "h_top_bucket": "VALIDATED_NOT_PLAUSIBLE",
      "l_top_bucket": "VALIDATED_NOT_PLAUSIBLE"
    }
  },
  "barrier_break_runs": [
    "v4_v3sniper_V2_val050_2026_04_11_030623",
    "v4_v3sniper_V3_val100_2026_04_11_030623",
    "v4_v3sniper_V4_val150_2026_04_11_030623",
    "v4_v3sniper_V5_val200_2026_04_11_030623"
  ],
  "global_bucket_failures": {
    "v3_hybrid": {
      "TRUNCATION_PRESSURE": 10,
      "VALIDATION_BUDGET_EXHAUSTED": 121,
      "CRITIC_GATE_OVERFILTERING": 17,
      "VALIDATED_NOT_PLAUSIBLE": 24
    },
    "v3_latent": {
      "VALIDATION_BUDGET_EXHAUSTED": 146,
      "TRUNCATION_PRESSURE": 4,
      "VALIDATED_NOT_PLAUSIBLE": 21
    }
  }
}